<?xml version="1.0" encoding="UTF-8"?>
<GenRun Id="synth_1" LaunchPart="xc7a100tcsg324-1" LaunchTime="1576159945">
  <File Type="PA-TCL" Name="TopLevel.tcl"/>
  <File Type="RDS-PROPCONSTRS" Name="TopLevel_drc_synth.rpt"/>
  <File Type="REPORTS-TCL" Name="TopLevel_reports.tcl"/>
  <File Type="RDS-RDS" Name="TopLevel.vds"/>
  <File Type="RDS-UTIL" Name="TopLevel_utilization_synth.rpt"/>
  <File Type="RDS-UTIL-PB" Name="TopLevel_utilization_synth.pb"/>
  <File Type="RDS-DCP" Name="TopLevel.dcp"/>
  <File Type="VDS-TIMINGSUMMARY" Name="TopLevel_timing_summary_synth.rpt"/>
  <File Type="VDS-TIMING-PB" Name="TopLevel_timing_summary_synth.pb"/>
  <FileSet Name="sources" Type="DesignSrcs" RelSrcDir="$PSRCDIR/sources_1">
    <Filter Type="Srcs"/>
    <File Path="$PSRCDIR/sources_1/ip/TriangleFifo/TriangleFifo.xci">
      <FileInfo>
        <Attr Name="UsedIn" Val="synthesis"/>
        <Attr Name="UsedIn" Val="implementation"/>
        <Attr Name="UsedIn" Val="simulation"/>
      </FileInfo>
    </File>
    <File Path="$PSRCDIR/sources_1/imports/VivadoProjects/Bresenham/Bresenham.srcs/sources_1/new/DrawLine.vhd">
      <FileInfo>
        <Attr Name="ImportPath" Val="$PPRDIR/../Bresenham/Bresenham.srcs/sources_1/new/DrawLine.vhd"/>
        <Attr Name="ImportTime" Val="1571744975"/>
        <Attr Name="UsedIn" Val="synthesis"/>
        <Attr Name="UsedIn" Val="simulation"/>
      </FileInfo>
    </File>
    <File Path="$PSRCDIR/sources_1/imports/new/LFSR16.vhd">
      <FileInfo>
        <Attr Name="ImportPath" Val="$PPRDIR/../LFSR/LFSR.srcs/sources_1/new/LFSR16.vhd"/>
        <Attr Name="ImportTime" Val="1572261227"/>
        <Attr Name="UsedIn" Val="synthesis"/>
        <Attr Name="UsedIn" Val="simulation"/>
      </FileInfo>
    </File>
    <File Path="$PSRCDIR/sources_1/new/Packages.vhd">
      <FileInfo>
        <Attr Name="UsedIn" Val="synthesis"/>
        <Attr Name="UsedIn" Val="simulation"/>
      </FileInfo>
    </File>
    <File Path="$PSRCDIR/sources_1/new/Triangles.vhd">
      <FileInfo>
        <Attr Name="UsedIn" Val="synthesis"/>
        <Attr Name="UsedIn" Val="simulation"/>
      </FileInfo>
    </File>
    <File Path="$PSRCDIR/sources_1/imports/new/VGATiming.vhd">
      <FileInfo>
        <Attr Name="ImportPath" Val="$PPRDIR/../VGA_scherm/VGA_scherm.srcs/sources_1/new/VGATiming.vhd"/>
        <Attr Name="ImportTime" Val="1570111474"/>
        <Attr Name="UsedIn" Val="synthesis"/>
        <Attr Name="UsedIn" Val="simulation"/>
      </FileInfo>
    </File>
    <File Path="$PSRCDIR/sources_1/new/VGA_RGB.vhd">
      <FileInfo>
        <Attr Name="UsedIn" Val="synthesis"/>
        <Attr Name="UsedIn" Val="simulation"/>
      </FileInfo>
    </File>
    <File Path="$PSRCDIR/sources_1/new/TopLevel.vhd">
      <FileInfo>
        <Attr Name="UsedIn" Val="synthesis"/>
        <Attr Name="UsedIn" Val="simulation"/>
      </FileInfo>
    </File>
    <File Path="$PPRDIR/FPA.coe">
      <FileInfo>
        <Attr Name="UsedIn" Val="synthesis"/>
        <Attr Name="UsedIn" Val="simulation"/>
      </FileInfo>
    </File>
    <Config>
      <Option Name="DesignMode" Val="RTL"/>
      <Option Name="TopModule" Val="TopLevel"/>
      <Option Name="TopAutoSet" Val="TRUE"/>
    </Config>
  </FileSet>
  <FileSet Name="constrs_in" Type="Constrs" RelSrcDir="$PSRCDIR/constrs_1">
    <Filter Type="Constrs"/>
    <File Path="$PSRCDIR/constrs_1/imports/VivadoProjects/Nexys-4-DDR-Master.xdc">
      <FileInfo>
        <Attr Name="ImportPath" Val="$PPRDIR/../Nexys-4-DDR-Master.xdc"/>
        <Attr Name="ImportTime" Val="1552382018"/>
        <Attr Name="UsedIn" Val="synthesis"/>
        <Attr Name="UsedIn" Val="implementation"/>
      </FileInfo>
    </File>
    <Config>
      <Option Name="TargetConstrsFile" Val="$PSRCDIR/constrs_1/imports/VivadoProjects/Nexys-4-DDR-Master.xdc"/>
      <Option Name="ConstrsType" Val="XDC"/>
    </Config>
  </FileSet>
  <FileSet Name="utils" Type="Utils" RelSrcDir="$PSRCDIR/utils_1">
    <Filter Type="Utils"/>
    <Config>
      <Option Name="TopAutoSet" Val="TRUE"/>
    </Config>
  </FileSet>
  <Strategy Version="1" Minor="2">
    <StratHandle Name="Vivado Synthesis Defaults" Flow="Vivado Synthesis 2019"/>
    <Step Id="synth_design"/>
  </Strategy>
  <BlockFileSet Type="BlockSrcs" Name="ClockingWizard"/>
  <BlockFileSet Type="BlockSrcs" Name="VideoMemory"/>
</GenRun>
